{
  "/[locale]/about/page": "app/[locale]/about/page.js",
  "/[locale]/blog/page": "app/[locale]/blog/page.js",
  "/[locale]/contact/page": "app/[locale]/contact/page.js",
  "/[locale]/faq/page": "app/[locale]/faq/page.js",
  "/[locale]/page": "app/[locale]/page.js",
  "/[locale]/products/[slug]/page": "app/[locale]/products/[slug]/page.js",
  "/[locale]/products/page": "app/[locale]/products/page.js",
  "/_global-error/page": "app/_global-error/page.js",
  "/_not-found/page": "app/_not-found/page.js",
  "/page": "app/page.js"
}